[
 {
  "business_nature_code": "BN3",
  "business_nature_name": "BNature3",
  "description": null,
  "docstatus": 0,
  "doctype": "Business Nature Master",
  "modified": "2024-03-28 09:44:23.055016",
  "name": "d7581b9267"
 },
 {
  "business_nature_code": "BN8",
  "business_nature_name": "Others",
  "description": null,
  "docstatus": 0,
  "doctype": "Business Nature Master",
  "modified": "2024-06-26 17:07:35.443036",
  "name": "fpnq39t5gb"
 },
 {
  "business_nature_code": "BN2",
  "business_nature_name": "BNature2",
  "description": null,
  "docstatus": 0,
  "doctype": "Business Nature Master",
  "modified": "2024-03-28 09:44:13.497541",
  "name": "bd5b364897"
 },
 {
  "business_nature_code": "BN1",
  "business_nature_name": "BNature 1",
  "description": null,
  "docstatus": 0,
  "doctype": "Business Nature Master",
  "modified": "2024-03-28 09:44:04.316281",
  "name": "7d92fdcab5"
 },
 {
  "business_nature_code": "BN5",
  "business_nature_name": "Agent",
  "description": null,
  "docstatus": 0,
  "doctype": "Business Nature Master",
  "modified": "2024-06-26 17:06:39.875762",
  "name": "fp6e1sbfik"
 },
 {
  "business_nature_code": "BN6",
  "business_nature_name": "Assembler",
  "description": null,
  "docstatus": 0,
  "doctype": "Business Nature Master",
  "modified": "2024-06-26 17:06:59.094829",
  "name": "fpcerghiti"
 },
 {
  "business_nature_code": "BN7",
  "business_nature_name": "Service Provider",
  "description": null,
  "docstatus": 0,
  "doctype": "Business Nature Master",
  "modified": "2024-06-26 17:07:13.807769",
  "name": "fph24or7hv"
 },
 {
  "business_nature_code": "BN4",
  "business_nature_name": "Trader",
  "description": null,
  "docstatus": 0,
  "doctype": "Business Nature Master",
  "modified": "2024-06-26 17:05:59.889761",
  "name": "fopu948jfb"
 }
]